pipewizard/__init__.py
pipewizard/main.py
pipewizard-0.0.1.dist-info/LICENSE
pipewizard-0.0.1.dist-info/METADATA
pipewizard-0.0.1.dist-info/WHEEL
pipewizard-0.0.1.dist-info/entry_points.txt
pipewizard-0.0.1.dist-info/top_level.txt
pipewizard-0.0.1.dist-info/RECORD
