Metadata-Version: 2.1
Name: pipewizard
Version: 0.0.1
Summary: A tool to help generate GitHub pipelines for Python projects
Home-page: https://github.com/atxpaul/pipewizard
Author: atxpaul
Author-email: 
Classifier: Programming Language :: Python :: 3.12
Classifier: License :: OSI Approved :: MIT License
Classifier: Operating System :: OS Independent
Requires-Python: >=3.10
License-File: LICENSE
Requires-Dist: questionary
Requires-Dist: rich
